Nuan.py
Naun-0.0.7.dist-info/LICENSE
Naun-0.0.7.dist-info/METADATA
Naun-0.0.7.dist-info/WHEEL
Naun-0.0.7.dist-info/top_level.txt
Naun-0.0.7.dist-info/RECORD
