Metadata-Version: 2.1
Name: Naun
Version: 0.0.7
Summary: This package implements video, and picture recognition using dlib and face_recognition.
Home-page: UNKNOWN
Author: Andreas Evensen
Author-email: Andreas.evensen11@gmail.com
License: UNKNOWN
Keywords: Facial Detection
Platform: UNKNOWN
Classifier: Development Status :: 3 - Alpha
Classifier: Intended Audience :: Developers
Classifier: License :: OSI Approved :: MIT License
Requires-Dist: dlib
Requires-Dist: face-recognition
